clarifai_utils/__init__.py
clarifai_utils/auth/__init__.py
clarifai_utils/auth/helper.py
clarifai_utils/client/__init__.py
clarifai_utils/client/abc.py
clarifai_utils/client/stub.py
clarifai_utils/data_upload/__init__.py
clarifai_utils/data_upload/base.py
clarifai_utils/data_upload/datasets.py
clarifai_utils/data_upload/upload.py
clarifai_utils/data_upload/utils.py
clarifai_utils/listing/__init__.py
clarifai_utils/listing/concepts.py
clarifai_utils/listing/datasets.py
clarifai_utils/listing/inputs.py
clarifai_utils/listing/installed_module_versions.py
clarifai_utils/listing/lister.py
clarifai_utils/listing/models.py
clarifai_utils/modules/__init__.py
clarifai_utils/modules/css.py
clarifai_utils/modules/pages.py
clarifai_utils/modules/style.css
clarifai_utils/urls/__init__.py
clarifai_utils/urls/helper.py
clarifai_utils-0.1.20.dist-info/LICENSE
clarifai_utils-0.1.20.dist-info/METADATA
clarifai_utils-0.1.20.dist-info/WHEEL
clarifai_utils-0.1.20.dist-info/top_level.txt
clarifai_utils-0.1.20.dist-info/RECORD
