Metadata-Version: 2.1
Name: clarifai-utils
Version: 0.1.20
Summary: Clarifai Python Utilities
Home-page: https://github.com/Clarifai/clarifai-python-utils
Author: Clarifai
Author-email: support@clarifai.com
License: Apache 2.0
Platform: UNKNOWN
Classifier: Topic :: Scientific/Engineering :: Artificial Intelligence
Classifier: Programming Language :: Python :: 3
Classifier: License :: OSI Approved :: Apache Software License
Classifier: Operating System :: OS Independent
Requires-Python: >=3.7
Requires-Dist: clarifai-grpc (>=7.12.0rc1)
